wakame/__init__.py
wakame/analyzer.py
wakame/charfilter.py
wakame/tokenfilter.py
wakame/tokenizer.py
wakame-0.3.0.dist-info/LICENSE.txt
wakame-0.3.0.dist-info/METADATA
wakame-0.3.0.dist-info/WHEEL
wakame-0.3.0.dist-info/top_level.txt
wakame-0.3.0.dist-info/RECORD
