Metadata-Version: 2.1
Name: wakame
Version: 0.3.0
Summary: Wrapper of `mecab`, which provide interface like `janome`.
Home-page: https://github.com/tenajima/wakame
Author: tenajima
Author-email: tenajima@gmail.com
License: UNKNOWN
Platform: UNKNOWN
Classifier: Programming Language :: Python :: 3
Classifier: License :: OSI Approved :: MIT License
Classifier: Operating System :: MacOS :: MacOS X
Classifier: Development Status :: 3 - Alpha
Requires-Dist: pandas
Requires-Dist: mecab-python3
